lab3/ex1.v
//f(A, B, C, D)= πM(2,6,8,9,10,11,14)
//nand gates

module q1(a, b, c, d, f);
    input a, b, c, d;
    output f;
    
    wire g0, g1, g2, g3, g4, g5, g6, g7, g8, g9;
    wire t0, t1; //cascading nand gates for f

    nand (g0, a, a); // a'
    nand (g1, c, c); // c'
    nand (g2, g0, g1);
    nand (g3, g2, g2); //a'c'

    nand (g4, b, d);
    nand (g5, g4, g4); //bd
    
    nand (g6, g0, d);
    nand (g7, g6, g6); // a'd

    nand (g8, g1, b);
    nand (g9, g8, g8); // c'b

    // nand (f, g3, g5, g7, g9);
    // this doesnt work because nand primitive only accepts 2 inputs lmeow
    
    nand (t0, g3, g5);
    nand (t1, g7, g9);
    
    nand (f, t0, t1);
    

endmodule

lab3/testbenches/ex1_tb.v
`timescale 1ns/1ns
`include "../ex1.v"

module q1_tb();
    reg a, b, c, d;
    wire f;
    
    q1 uut(a, b, c, d, f);
    
    initial begin
        $dumpfile("q1_tb.vcd");
        $dumpvars(0, q1_tb);
        
        $display("Time\t a b c d | f | Expected");
        $display("-----------------------------------");
        
        // Test all 16 combinations
        a=1'b0; b=1'b0; c=1'b0; d=1'b0;
        #20 $display("%0t\t %b %b %b %b | %b | 1", $time, a, b, c, d, f);
        
        a=1'b0; b=1'b0; c=1'b0; d=1'b1;
        #20 $display("%0t\t %b %b %b %b | %b | 1", $time, a, b, c, d, f);
        
        a=1'b0; b=1'b0; c=1'b1; d=1'b0;  // m2 - maxterm
        #20 $display("%0t\t %b %b %b %b | %b | 0", $time, a, b, c, d, f);
        
        a=1'b0; b=1'b0; c=1'b1; d=1'b1;
        #20 $display("%0t\t %b %b %b %b | %b | 1", $time, a, b, c, d, f);
        
        a=1'b0; b=1'b1; c=1'b0; d=1'b0;
        #20 $display("%0t\t %b %b %b %b | %b | 1", $time, a, b, c, d, f);
        
        a=1'b0; b=1'b1; c=1'b0; d=1'b1;
        #20 $display("%0t\t %b %b %b %b | %b | 1", $time, a, b, c, d, f);
        
        a=1'b0; b=1'b1; c=1'b1; d=1'b0;  // m6 - maxterm
        #20 $display("%0t\t %b %b %b %b | %b | 0", $time, a, b, c, d, f);
        
        a=1'b0; b=1'b1; c=1'b1; d=1'b1;
        #20 $display("%0t\t %b %b %b %b | %b | 1", $time, a, b, c, d, f);
        
        a=1'b1; b=1'b0; c=1'b0; d=1'b0;  // m8 - maxterm
        #20 $display("%0t\t %b %b %b %b | %b | 0", $time, a, b, c, d, f);
        
        a=1'b1; b=1'b0; c=1'b0; d=1'b1;  // m9 - maxterm
        #20 $display("%0t\t %b %b %b %b | %b | 0", $time, a, b, c, d, f);
        
        a=1'b1; b=1'b0; c=1'b1; d=1'b0;  // m10 - maxterm
        #20 $display("%0t\t %b %b %b %b | %b | 0", $time, a, b, c, d, f);
        
        a=1'b1; b=1'b0; c=1'b1; d=1'b1;  // m11 - maxterm
        #20 $display("%0t\t %b %b %b %b | %b | 0", $time, a, b, c, d, f);
        
        a=1'b1; b=1'b1; c=1'b0; d=1'b0;
        #20 $display("%0t\t %b %b %b %b | %b | 1", $time, a, b, c, d, f);
        
        a=1'b1; b=1'b1; c=1'b0; d=1'b1;
        #20 $display("%0t\t %b %b %b %b | %b | 1", $time, a, b, c, d, f);
        
        a=1'b1; b=1'b1; c=1'b1; d=1'b0;  // m14 - maxterm
        #20 $display("%0t\t %b %b %b %b | %b | 0", $time, a, b, c, d, f);
        
        a=1'b1; b=1'b1; c=1'b1; d=1'b1;
        #20 $display("%0t\t %b %b %b %b | %b | 1", $time, a, b, c, d, f);
        
        $display("\nSimulation completed");
        $finish;
    end
endmodule

lab3/testbenches/q1_tb.vcd
$date
	Fri Jan 16 16:43:53 2026
$end
$version
	Icarus Verilog
$end
$timescale
	1ns
$end
$scope module q1_tb $end
$var wire 1 ! f $end
$var reg 1 " a $end
$var reg 1 # b $end
$var reg 1 $ c $end
$var reg 1 % d $end
$scope module uut $end
$var wire 1 " a $end
$var wire 1 # b $end
$var wire 1 $ c $end
$var wire 1 % d $end
$var wire 1 ! f $end
$var wire 1 & g0 $end
$var wire 1 ' g1 $end
$var wire 1 ( g2 $end
$var wire 1 ) g3 $end
$var wire 1 * g4 $end
$var wire 1 + g5 $end
$var wire 1 , g6 $end
$var wire 1 - g7 $end
$var wire 1 . g8 $end
$var wire 1 / g9 $end
$var wire 1 0 t0 $end
$var wire 1 1 t1 $end
$upscope $end
$upscope $end
$enddefinitions $end
$comment Show the parameter values. $end
$dumpall
$end
#0
$dumpvars
11
10
0/
1.
0-
1,
0+
1*
1)
0(
1'
1&
0%
0$
0#
0"
0!
$end
#20
1-
0,
1%
#40
0)
0-
1(
1,
0'
0%
1$
#60
1-
0,
1%
#80
1)
1/
0-
0(
0.
1,
1'
0%
0$
1#
#100
1!
00
01
1+
1-
0*
0,
1%
#120
0!
10
11
0)
0/
0+
0-
1(
1.
1*
1,
0'
0%
1$
#140
1+
1-
0*
0,
1%
#160
0-
0+
1,
1'
1*
0&
0%
0$
0#
1"
#180
1%
#200
0'
0%
1$
#220
1%
#240
1/
0.
1'
0%
0$
1#
#260
1+
0*
1%
#280
0/
0+
1.
1*
0'
0%
1$
#300
1+
0*
1%
