lab3/ex1.v
//f(A, B, C, D)= πM(2,6,8,9,10,11,14)
//nand gates

module q1(a, b, c, d, f);
    input a, b, c, d;
    output f;
    
    wire g0, g1, g2, g3, g4, g5, g6, g7, g8, g9;
    wire n3, n5, n7, n9; // inverse for product terms 
    wire t0, t1; //cascading nand gates for f

    nand (g0, a, a); // a'
    nand (g1, c, c); // c'
    nand (g2, g0, g1);
    nand (g3, g2, g2); //a'c'

    nand (g4, b, d);
    nand (g5, g4, g4); //bd
    
    nand (g6, g0, d);
    nand (g7, g6, g6); // a'd

    nand (g8, g1, b);
    nand (g9, g8, g8); // c'b

    //nand (f, g3, g5, g7, g9);
    // this doesnt work because nand primitive only accepts 2 inputs lmeow

    nand (n3, g3, g3);
    nand (n5, g5, g5);
    nand (o0, n3, n5);

    nand (n7, g7, g7);
    nand (n9, g9, g9);
    nand (o1, n7, n9);
   
    nand (t0, o0, o0);
    nand (t1, o1, o1);
    nand (f, t0, t1); 
    

endmodule

lab3/testbenches/ex1_tb.v
`timescale 1ns/1ns
`include "../ex1.v"

module q1_tb;
    reg a, b, c, d;
    wire f;

    q1 uut (.a(a), .b(b), .c(c), .d(d), .f(f));

    task apply;
        input aa, bb, cc, dd;
        input exp;
        begin
            a = aa; b = bb; c = cc; d = dd;
            #10;
            $display("%0t\t %b %b %b %b | %b | %b",
                     $time, a, b, c, d, f, exp);
        end
    endtask

    initial begin
        $dumpfile("q1_tb.vcd");
        $dumpvars(0, q1_tb);

        $display("Time\t a b c d | f | Expected");
        $display("-----------------------------------");

        apply(0,0,0,0,1);
        apply(0,0,0,1,1);
        apply(0,0,1,0,0); // m2
        apply(0,0,1,1,1);

        apply(0,1,0,0,1);
        apply(0,1,0,1,1);
        apply(0,1,1,0,0); // m6
        apply(0,1,1,1,1);

        apply(1,0,0,0,0); // m8
        apply(1,0,0,1,0); // m9
        apply(1,0,1,0,0); // m10
        apply(1,0,1,1,0); // m11

        apply(1,1,0,0,1);
        apply(1,1,0,1,1);
        apply(1,1,1,0,0); // m14
        apply(1,1,1,1,1);

        $display("\nSimulation completed");
        $finish;
    end
endmodule

lab3/testbenches/q1_tb.vcd
$date
	Sat Jan 17 00:26:11 2026
$end
$version
	Icarus Verilog
$end
$timescale
	1ns
$end
$scope module q1_tb $end
$var wire 1 ! f $end
$var reg 1 " a $end
$var reg 1 # b $end
$var reg 1 $ c $end
$var reg 1 % d $end
$scope module uut $end
$var wire 1 " a $end
$var wire 1 # b $end
$var wire 1 $ c $end
$var wire 1 % d $end
$var wire 1 ! f $end
$var wire 1 & g0 $end
$var wire 1 ' g1 $end
$var wire 1 ( g2 $end
$var wire 1 ) g3 $end
$var wire 1 * g4 $end
$var wire 1 + g5 $end
$var wire 1 , g6 $end
$var wire 1 - g7 $end
$var wire 1 . g8 $end
$var wire 1 / g9 $end
$var wire 1 0 n3 $end
$var wire 1 1 n5 $end
$var wire 1 2 n7 $end
$var wire 1 3 n9 $end
$var wire 1 4 o0 $end
$var wire 1 5 o1 $end
$var wire 1 6 t0 $end
$var wire 1 7 t1 $end
$upscope $end
$scope task apply $end
$var reg 1 8 aa $end
$var reg 1 9 bb $end
$var reg 1 : cc $end
$var reg 1 ; dd $end
$var reg 1 < exp $end
$upscope $end
$upscope $end
$enddefinitions $end
$comment Show the parameter values. $end
$dumpall
$end
#0
$dumpvars
1<
0;
0:
09
08
17
06
05
14
13
12
11
00
0/
1.
0-
1,
0+
1*
1)
0(
1'
1&
0%
0$
0#
0"
1!
$end
#10
07
15
02
1-
0,
1%
1;
#20
0!
16
17
04
05
10
12
0)
0-
1(
1,
0'
0%
1$
0<
0;
1:
#30
1!
07
15
02
1-
0,
1%
1<
1;
#40
06
14
00
03
12
1)
1/
0-
0(
0.
1,
1'
0%
0$
1#
0;
0:
19
#50
01
02
1+
1-
0*
0,
1%
1;
#60
0!
16
17
04
05
10
13
11
12
0)
0/
0+
0-
1(
1.
1*
1,
0'
0%
1$
0<
0;
1:
#70
1!
06
07
14
15
01
02
1+
1-
0*
0,
1%
1<
1;
#80
0!
17
16
05
04
12
11
0-
0+
1,
1'
1*
0&
0%
0$
0#
1"
0<
0;
0:
09
18
#90
1%
1;
#100
0'
0%
1$
0;
1:
#110
1%
1;
#120
1!
07
15
03
1/
0.
1'
0%
0$
1#
1<
0;
0:
19
#130
06
14
01
1+
0*
1%
1;
#140
0!
17
16
05
04
13
11
0/
0+
1.
1*
0'
0%
1$
0<
0;
1:
#150
1!
06
14
01
1+
0*
1%
1<
1;
