lab3/ex3.v
// f(A, B, C, D) = ∑m(1,3,5,7,9) + D(6,12,13)


module q3(a, b, c, d, f);
    input a, b, c, d;
    output f;

    wire g0, g1, g2, g3, g4;

    nor (g0, d, d); //d'
    //nor (g1, c, c); //c'

    nor (g2, g0, a); // demorgans -> a'd
    
    nor (g3, g0, c); // demorgans -> c'd

    nor (g4, g2, g3);
    nor (f, g4, g4);

endmodule

lab3/testbenches/ex3_tb.v
`timescale 1ns/1ns
`include "../ex3.v"

module q3_tb();
    reg a, b, c, d;
    wire f;
    
    q3 uut(a, b, c, d, f);
    
    initial begin
        $dumpfile("q3_tb.vcd");
        $dumpvars(0, q3_tb);
        
        $display("ABCD | f | Expected");
        $display("-----|---|----------");
        
        {a,b,c,d} = 4'b0000; #10 $display("%b | %b | 0", {a,b,c,d}, f);
        {a,b,c,d} = 4'b0001; #10 $display("%b | %b | 1 (m1)", {a,b,c,d}, f);
        {a,b,c,d} = 4'b0010; #10 $display("%b | %b | 0", {a,b,c,d}, f);
        {a,b,c,d} = 4'b0011; #10 $display("%b | %b | 1 (m3)", {a,b,c,d}, f);
        {a,b,c,d} = 4'b0100; #10 $display("%b | %b | 0", {a,b,c,d}, f);
        {a,b,c,d} = 4'b0101; #10 $display("%b | %b | 1 (m5)", {a,b,c,d}, f);
        {a,b,c,d} = 4'b0110; #10 $display("%b | %b | X (DC)", {a,b,c,d}, f);
        {a,b,c,d} = 4'b0111; #10 $display("%b | %b | 1 (m7)", {a,b,c,d}, f);
        {a,b,c,d} = 4'b1000; #10 $display("%b | %b | 0", {a,b,c,d}, f);
        {a,b,c,d} = 4'b1001; #10 $display("%b | %b | 1 (m9)", {a,b,c,d}, f);
        {a,b,c,d} = 4'b1010; #10 $display("%b | %b | 0", {a,b,c,d}, f);
        {a,b,c,d} = 4'b1011; #10 $display("%b | %b | 0", {a,b,c,d}, f);
        {a,b,c,d} = 4'b1100; #10 $display("%b | %b | X (DC)", {a,b,c,d}, f);
        {a,b,c,d} = 4'b1101; #10 $display("%b | %b | X (DC)", {a,b,c,d}, f);
        {a,b,c,d} = 4'b1110; #10 $display("%b | %b | 0", {a,b,c,d}, f);
        {a,b,c,d} = 4'b1111; #10 $display("%b | %b | 0", {a,b,c,d}, f);
        
        $finish;
    end
endmodule

lab3/testbenches/q3_tb.vcd
$date
	Sat Jan 17 23:36:34 2026
$end
$version
	Icarus Verilog
$end
$timescale
	1ns
$end
$scope module q3_tb $end
$var wire 1 ! f $end
$var reg 1 " a $end
$var reg 1 # b $end
$var reg 1 $ c $end
$var reg 1 % d $end
$scope module uut $end
$var wire 1 " a $end
$var wire 1 # b $end
$var wire 1 $ c $end
$var wire 1 % d $end
$var wire 1 ! f $end
$var wire 1 & g0 $end
$var wire 1 ' g2 $end
$var wire 1 ( g3 $end
$var wire 1 ) g4 $end
$upscope $end
$upscope $end
$enddefinitions $end
$comment Show the parameter values. $end
$dumpall
$end
#0
$dumpvars
1)
0(
0'
1&
0%
0$
0#
0"
0!
$end
#10
1!
0)
1'
1(
0&
1%
#20
0!
1)
0'
0(
1&
1$
0%
#30
1!
0)
1'
0&
1%
#40
0!
1)
0'
1&
1#
0$
0%
#50
1!
0)
1'
1(
0&
1%
#60
0!
1)
0'
0(
1&
1$
0%
#70
1!
0)
1'
0&
1%
#80
0!
1)
0'
1&
1"
0#
0$
0%
#90
1!
0)
1(
0&
1%
#100
0!
1)
0(
1&
1$
0%
#110
0&
1%
#120
1&
1#
0$
0%
#130
1!
0)
1(
0&
1%
#140
0!
1)
0(
1&
1$
0%
#150
0&
1%
