lab3/ex4.v
// f(A, B, C, D)= πM(4,9,12,13,14) + D(5,6,11,15)

module q4(a, b, c, d, f);
    input a, b, c, d;
    output f;

    wire g0, g1, g2, g3, g4, g5, g6, g7;

    nand (g0, c, c);
    nand (g1, d, d);

    nand (g2, a, d); // a' + d'

    nand (g3, b, g0); // b' + c

    nand (g4, b, g1); // b' + d 

    nand (g5, g2, g3);
    nand (g6, g5, g5);
    nand (g7, g6, g4);
    nand (f, g7, g7);

endmodule

lab3/testbenches/ex4_tb.v
`timescale 1ns/1ns
`include "../ex4.v"

module q4_tb;

    reg a, b, c, d;
    wire f;

    q4 dut (
        .a(a),
        .b(b),
        .c(c),
        .d(d),
        .f(f)
    );

    task apply;
        input [3:0] v;
        input [15*8:1] note;
        begin
            {a,b,c,d} = v;
            #10;
            $display("%4t  %b%b%b%b   %b     %s",
                     $time, a,b,c,d, f, note);
        end
    endtask

    initial begin
        $dumpfile("q4_tb.vcd");
        $dumpvars(0, q4_tb);

        $display("Time  ABCD   f   Remark");
        $display("------------------------------");

        apply(4'b0000, "ON  (allowed 1)");
        apply(4'b0001, "ON  (allowed 1)");
        apply(4'b0010, "ON  (allowed 1)");
        apply(4'b0011, "ON  (allowed 1)");

        apply(4'b0100, "OFF (maxterm)");
        apply(4'b0101, "DC  (dont care)");
        apply(4'b0110, "DC  (dont care)");
        apply(4'b0111, "ON  (allowed 1)");

        apply(4'b1000, "ON  (allowed 1)");
        apply(4'b1001, "OFF (maxterm)");
        apply(4'b1010, "ON  (allowed 1)");
        apply(4'b1011, "DC  (dont care)");

        apply(4'b1100, "OFF (maxterm)");
        apply(4'b1101, "OFF (maxterm)");
        apply(4'b1110, "OFF (maxterm)");
        apply(4'b1111, "DC  (dont care)");

        $display("\nLegend:");
        $display("OFF : forced 0 (πM)");
        $display("ON  : forced 1");
        $display("DC  : don't-care");

        $finish;
    end

endmodule

lab3/testbenches/q4_tb.vcd
$date
	Sun Jan 18 01:06:14 2026
$end
$version
	Icarus Verilog
$end
$timescale
	1ns
$end
$scope module q4_tb $end
$var wire 1 ! f $end
$var reg 1 " a $end
$var reg 1 # b $end
$var reg 1 $ c $end
$var reg 1 % d $end
$scope module dut $end
$var wire 1 " a $end
$var wire 1 # b $end
$var wire 1 $ c $end
$var wire 1 % d $end
$var wire 1 ! f $end
$var wire 1 & g0 $end
$var wire 1 ' g1 $end
$var wire 1 ( g2 $end
$var wire 1 ) g3 $end
$var wire 1 * g4 $end
$var wire 1 + g5 $end
$var wire 1 , g6 $end
$var wire 1 - g7 $end
$upscope $end
$scope task apply $end
$var reg 120 . note [120:1] $end
$var reg 4 / v [3:0] $end
$upscope $end
$upscope $end
$enddefinitions $end
$comment Show the parameter values. $end
$dumpall
$end
#0
$dumpvars
b0 /
b10011110100111000100000001000000010100001100001011011000110110001101111011101110110010101100100001000000011000100101001 .
0-
1,
0+
1*
1)
1(
1'
1&
0%
0$
0#
0"
1!
$end
#10
0'
1%
b1 /
#20
0&
1'
1$
0%
b10 /
#30
0'
1%
b11 /
#40
0,
0!
1+
1-
0)
0*
1&
1'
1#
0$
0%
b1001111010001100100011000100000001010000110110101100001011110000111010001100101011100100110110100101001 .
b100 /
#50
1*
0'
1%
b10001000100001100100000001000000010100001100100011011110110111001110100001000000110001101100001011100100110010100101001 .
b101 /
#60
1,
0+
1)
0*
0&
1'
1$
0%
b110 /
#70
1!
0-
1*
0'
1%
b10011110100111000100000001000000010100001100001011011000110110001101111011101110110010101100100001000000011000100101001 .
b111 /
#80
1&
1'
1"
0#
0$
0%
b1000 /
#90
0!
1-
0,
1+
0'
0(
1%
b1001111010001100100011000100000001010000110110101100001011110000111010001100101011100100110110100101001 .
b1001 /
#100
1!
0-
1,
0+
0&
1'
1(
1$
0%
b10011110100111000100000001000000010100001100001011011000110110001101111011101110110010101100100001000000011000100101001 .
b1010 /
#110
0!
1-
0,
1+
0'
0(
1%
b10001000100001100100000001000000010100001100100011011110110111001110100001000000110001101100001011100100110010100101001 .
b1011 /
#120
0)
0*
1&
1'
1(
1#
0$
0%
b1001111010001100100011000100000001010000110110101100001011110000111010001100101011100100110110100101001 .
b1100 /
#130
1*
0'
0(
1%
b1101 /
#140
1,
0+
1)
0*
0&
1'
1(
1$
0%
b1110 /
#150
0,
1*
1+
0'
0(
1%
b10001000100001100100000001000000010100001100100011011110110111001110100001000000110001101100001011100100110010100101001 .
b1111 /
