lab2/ex3.v
module q3(x1, x2, x3, x4, out);
    input x1, x2, x3, x4;
    output out;

    assign out = (x2 & x3 & x4) | (x1 & x3 & x4) | (x1 & x2 & x4) | (x1 & x2 & x3);

endmodule

lab2/tb-vcd/ex3_tb.v
`timescale 1ns/1ns
`include "ex3.v"

module q3_tb();
    reg x1, x2, x3, x4;
    wire f;
    
    q3 uut(x1, x2, x3, x4, f);
    
    initial begin
        $dumpfile("ex3_tb.vcd");
        $dumpvars(0, q3_tb);
        
        $display("x1 x2 x3 x4 | f");
        $display("-------------");
        
        // Test all 16 combinations
        {x1,x2,x3,x4} = 4'b0000; #10 $display("%b  %b  %b  %b  | %b", x1,x2,x3,x4,f);
        {x1,x2,x3,x4} = 4'b0001; #10 $display("%b  %b  %b  %b  | %b", x1,x2,x3,x4,f);
        {x1,x2,x3,x4} = 4'b0010; #10 $display("%b  %b  %b  %b  | %b", x1,x2,x3,x4,f);
        {x1,x2,x3,x4} = 4'b0011; #10 $display("%b  %b  %b  %b  | %b", x1,x2,x3,x4,f);
        {x1,x2,x3,x4} = 4'b0100; #10 $display("%b  %b  %b  %b  | %b", x1,x2,x3,x4,f);
        {x1,x2,x3,x4} = 4'b0101; #10 $display("%b  %b  %b  %b  | %b", x1,x2,x3,x4,f);
        {x1,x2,x3,x4} = 4'b0110; #10 $display("%b  %b  %b  %b  | %b", x1,x2,x3,x4,f);
        {x1,x2,x3,x4} = 4'b0111; #10 $display("%b  %b  %b  %b  | %b", x1,x2,x3,x4,f);
        {x1,x2,x3,x4} = 4'b1000; #10 $display("%b  %b  %b  %b  | %b", x1,x2,x3,x4,f);
        {x1,x2,x3,x4} = 4'b1001; #10 $display("%b  %b  %b  %b  | %b", x1,x2,x3,x4,f);
        {x1,x2,x3,x4} = 4'b1010; #10 $display("%b  %b  %b  %b  | %b", x1,x2,x3,x4,f);
        {x1,x2,x3,x4} = 4'b1011; #10 $display("%b  %b  %b  %b  | %b", x1,x2,x3,x4,f);
        {x1,x2,x3,x4} = 4'b1100; #10 $display("%b  %b  %b  %b  | %b", x1,x2,x3,x4,f);
        {x1,x2,x3,x4} = 4'b1101; #10 $display("%b  %b  %b  %b  | %b", x1,x2,x3,x4,f);
        {x1,x2,x3,x4} = 4'b1110; #10 $display("%b  %b  %b  %b  | %b", x1,x2,x3,x4,f);
        {x1,x2,x3,x4} = 4'b1111; #10 $display("%b  %b  %b  %b  | %b", x1,x2,x3,x4,f);
        
        $finish;
    end
endmodule

lab2/tb-vcd/ex3_tb.vcd
$date
	Fri Jan 16 16:06:05 2026
$end
$version
	Icarus Verilog
$end
$timescale
	1ns
$end
$scope module q3_tb $end
$var wire 1 ! f $end
$var reg 1 " x1 $end
$var reg 1 # x2 $end
$var reg 1 $ x3 $end
$var reg 1 % x4 $end
$scope module uut $end
$var wire 1 ! out $end
$var wire 1 " x1 $end
$var wire 1 # x2 $end
$var wire 1 $ x3 $end
$var wire 1 % x4 $end
$upscope $end
$upscope $end
$enddefinitions $end
$comment Show the parameter values. $end
$dumpall
$end
#0
$dumpvars
0%
0$
0#
0"
0!
$end
#10
1%
#20
1$
0%
#30
1%
#40
1#
0$
0%
#50
1%
#60
1$
0%
#70
1!
1%
#80
0!
1"
0#
0$
0%
#90
1%
#100
1$
0%
#110
1!
1%
#120
0!
1#
0$
0%
#130
1!
1%
#140
1$
0%
#150
1%
