lab1/ex1-i.v
module ex1(a, b, c, d, f);
    input a, b, c, d;
    output f;
    wire g0, g1, g2, g3, g4, g5, g6; // i can create a wire by gate(wire, in1, in2);

    and (g0, a, b);
    and (g1, a, b);
    or (g2, g0, c);
    or (g3, g1, c);
    not (g4, g2);
    and (g5, g4, d);
    and (g6, g3, d);
    and (f, g5, g6);

endmodule

lab1/ex1-prim_tb.v
// to run the file:
// iverilog -o ex1_prim_sim ex1-prim_tb.v
// vvp ex1_prim_sim
// gtkwave ex1-prim_tb.v



`timescale 1ns/1ns
`include "ex1-primitive.v" //Name of the Verilog file

module ex1_tb();
reg a, b, c, d; //Input
wire f; //Output
ex1 uut(a, b, c, d, f);

initial
begin //Instantiation of the module

$dumpfile("ex1_prim_tb.vcd");
$dumpvars(0, ex1_tb); // 2^4 == 16 combinations

a=1'b0; b=1'b0; c=1'b0; d=1'b0;
#20;
a=1'b0; b=1'b0; c=1'b0; d=1'b1;
#20;
a=1'b0; b=1'b0; c=1'b1; d=1'b0;
#20;
a=1'b0; b=1'b0; c=1'b1; d=1'b1;
#20;
a=1'b0; b=1'b1; c=1'b0; d=1'b0;
#20;
a=1'b0; b=1'b1; c=1'b0; d=1'b1;
#20;
a=1'b0; b=1'b1; c=1'b1; d=1'b0;
#20;
a=1'b0; b=1'b1; c=1'b1; d=1'b1;
#20;
a=1'b1; b=1'b0; c=1'b0; d=1'b0;
#20;
a=1'b1; b=1'b0; c=1'b0; d=1'b1;
#20;
a=1'b1; b=1'b0; c=1'b1; d=1'b0;
#20;
a=1'b1; b=1'b0; c=1'b1; d=1'b1;
#20;
a=1'b1; b=1'b1; c=1'b0; d=1'b0;
#20;
a=1'b1; b=1'b1; c=1'b0; d=1'b1;
#20;
a=1'b1; b=1'b1; c=1'b1; d=1'b0;
#20;
a=1'b1; b=1'b1; c=1'b1; d=1'b1;
#20;

$display("Simulation completed");
$finish;
end
endmodule

lab1/vcds/ex1_prim_tb.vcd
$date
	Fri Jan 16 04:14:46 2026
$end
$version
	Icarus Verilog
$end
$timescale
	1ns
$end
$scope module ex1_tb $end
$var wire 1 ! f $end
$var reg 1 " a $end
$var reg 1 # b $end
$var reg 1 $ c $end
$var reg 1 % d $end
$scope module uut $end
$var wire 1 " a $end
$var wire 1 # b $end
$var wire 1 $ c $end
$var wire 1 % d $end
$var wire 1 ! f $end
$var wire 1 & g0 $end
$var wire 1 ' g1 $end
$var wire 1 ( g2 $end
$var wire 1 ) g3 $end
$var wire 1 * g4 $end
$var wire 1 + g5 $end
$var wire 1 , g6 $end
$upscope $end
$upscope $end
$enddefinitions $end
$comment Show the parameter values. $end
$dumpall
$end
#0
$dumpvars
0,
0+
1*
0)
0(
0'
0&
0%
0$
0#
0"
0!
$end
#20
1+
1%
#40
0*
0+
1(
1)
0%
1$
#60
1,
1%
#80
1*
0,
0(
0)
0%
0$
1#
#100
1+
1%
#120
0*
0+
1(
1)
0%
1$
#140
1,
1%
#160
1*
0,
0(
0)
0%
0$
0#
1"
#180
1+
1%
#200
0*
0+
1(
1)
0%
1$
#220
1,
1%
#240
0,
1&
1'
0%
0$
1#
#260
1,
1%
#280
0,
0%
1$
#300
1,
1%
